cex_services/__init__.py
cex_services/binance.py
cex_services/bitget.py
cex_services/bitmex.py
cex_services/bybit.py
cex_services/gateio.py
cex_services/htx.py
cex_services/kucoin.py
cex_services/okx.py
cex_services/utils.py
cex_services/exchanges/__init__.py
cex_services/exchanges/base.py
cex_services/exchanges/biget.py
cex_services/exchanges/binance.py
cex_services/exchanges/bitget.py
cex_services/exchanges/bitmex.py
cex_services/exchanges/bybit.py
cex_services/exchanges/gateio.py
cex_services/exchanges/htx.py
cex_services/exchanges/kucoin.py
cex_services/exchanges/okx.py
cex_services/parsers/__init__.py
cex_services/parsers/base.py
cex_services/parsers/biget.py
cex_services/parsers/binance.py
cex_services/parsers/bitget.py
cex_services/parsers/bitmex.py
cex_services/parsers/bybit.py
cex_services/parsers/gateio.py
cex_services/parsers/htx.py
cex_services/parsers/kucoin.py
cex_services/parsers/okx.py
cex_services-1.0.4.dist-info/METADATA
cex_services-1.0.4.dist-info/WHEEL
cex_services-1.0.4.dist-info/top_level.txt
cex_services-1.0.4.dist-info/RECORD
