Metadata-Version: 2.1
Name: cex_services
Version: 1.0.4
